qsimcirq/__init__.py
qsimcirq/_version.py
qsimcirq/py.typed
qsimcirq/qsim_avx2.cp311-win_amd64.pyd
qsimcirq/qsim_avx512.cp311-win_amd64.pyd
qsimcirq/qsim_basic.cp311-win_amd64.pyd
qsimcirq/qsim_circuit.py
qsimcirq/qsim_decide.cp311-win_amd64.pyd
qsimcirq/qsim_simulator.py
qsimcirq/qsim_sse.cp311-win_amd64.pyd
qsimcirq/qsimh_simulator.py
qsimcirq-0.22.0.dist-info/licenses/LICENSE
qsimcirq-0.22.0.dist-info/METADATA
qsimcirq-0.22.0.dist-info/WHEEL
qsimcirq-0.22.0.dist-info/top_level.txt
qsimcirq-0.22.0.dist-info/RECORD
