Metadata-Version: 2.4
Name: qsimcirq
Version: 0.22.0
Summary: Schrödinger and Schrödinger-Feynman simulators for quantum circuits.
Home-page: https://github.com/quantumlib/qsim
Author: The qsim/qsimh Developers
Author-email: qsim-qsimh-dev@googlegroups.com
Maintainer: Google Quantum AI open-source maintainers
Maintainer-email: quantum-oss-maintainers@google.com
License: Apache-2.0
Keywords: algorithms,api,application programming interface,cirq,google quantum,google,nisq,python,quantum algorithm development,quantum circuit simulator,quantum computer simulator,quantum computing,quantum computing research,quantum programming,quantum simulation,quantum,schrödinger-feynman simulation,sdk,simulation,state vector simulator,software development kit
Classifier: Development Status :: 5 - Production/Stable
Classifier: Environment :: GPU :: NVIDIA CUDA
Classifier: Intended Audience :: Developers
Classifier: Intended Audience :: Science/Research
Classifier: Operating System :: MacOS :: MacOS X
Classifier: Operating System :: Microsoft :: Windows
Classifier: Operating System :: POSIX :: Linux
Classifier: Programming Language :: C++
Classifier: Programming Language :: Python :: 3
Classifier: Programming Language :: Python :: 3.10
Classifier: Programming Language :: Python :: 3.11
Classifier: Programming Language :: Python :: 3.12
Classifier: Programming Language :: Python :: 3.13
Classifier: Topic :: Scientific/Engineering :: Quantum Computing
Classifier: Topic :: Software Development :: Libraries :: Python Modules
Classifier: Typing :: Typed
Requires-Python: >=3.10.0
License-File: LICENSE
Requires-Dist: absl-py
Requires-Dist: cirq-core~=1.0
Requires-Dist: numpy>=1.26.0
Requires-Dist: pybind11[global]
Requires-Dist: typing_extensions
Requires-Dist: setuptools>=75.2.0
Provides-Extra: dev
Requires-Dist: black~=25.1.0; extra == "dev"
Requires-Dist: cmake~=3.31.0; extra == "dev"
Requires-Dist: flynt~=1.0; extra == "dev"
Requires-Dist: pytest; extra == "dev"
Requires-Dist: pytest-xdist; extra == "dev"
Requires-Dist: py-cpuinfo; extra == "dev"
Dynamic: author
Dynamic: author-email
Dynamic: classifier
Dynamic: description
Dynamic: description-content-type
Dynamic: home-page
Dynamic: keywords
Dynamic: license
Dynamic: license-file
Dynamic: maintainer
Dynamic: maintainer-email
Dynamic: provides-extra
Dynamic: requires-dist
Dynamic: requires-python
Dynamic: summary
